pretix_newsletter_ml/__init__.py
pretix_newsletter_ml/apps.py
pretix_newsletter_ml/signals.py
pretix_newsletter_ml/tasks.py
pretix_newsletter_ml/urls.py
pretix_newsletter_ml/views.py
pretix_newsletter_ml/locale/django.pot
pretix_newsletter_ml/locale/ar/LC_MESSAGES/django.po
pretix_newsletter_ml/locale/ca/LC_MESSAGES/django.po
pretix_newsletter_ml/locale/cs/LC_MESSAGES/django.po
pretix_newsletter_ml/locale/da/LC_MESSAGES/django.po
pretix_newsletter_ml/locale/de/LC_MESSAGES/django.po
pretix_newsletter_ml/locale/de_Informal/.gitkeep
pretix_newsletter_ml/locale/de_Informal/LC_MESSAGES/django.po
pretix_newsletter_ml/locale/el/LC_MESSAGES/django.po
pretix_newsletter_ml/locale/es/LC_MESSAGES/django.po
pretix_newsletter_ml/locale/fi/LC_MESSAGES/django.po
pretix_newsletter_ml/locale/fr/LC_MESSAGES/django.po
pretix_newsletter_ml/locale/hr/LC_MESSAGES/django.po
pretix_newsletter_ml/locale/it/LC_MESSAGES/django.po
pretix_newsletter_ml/locale/ja/LC_MESSAGES/django.po
pretix_newsletter_ml/locale/lv/LC_MESSAGES/django.po
pretix_newsletter_ml/locale/nl/LC_MESSAGES/django.po
pretix_newsletter_ml/locale/nl_BE/LC_MESSAGES/django.po
pretix_newsletter_ml/locale/nl_Informal/LC_MESSAGES/django.po
pretix_newsletter_ml/locale/pl/LC_MESSAGES/django.po
pretix_newsletter_ml/locale/pl_Informal/LC_MESSAGES/django.po
pretix_newsletter_ml/locale/pt/LC_MESSAGES/django.po
pretix_newsletter_ml/locale/pt_BR/LC_MESSAGES/django.po
pretix_newsletter_ml/locale/ru/LC_MESSAGES/django.po
pretix_newsletter_ml/locale/si/LC_MESSAGES/django.po
pretix_newsletter_ml/locale/sl/LC_MESSAGES/django.po
pretix_newsletter_ml/locale/sv/LC_MESSAGES/django.po
pretix_newsletter_ml/locale/tr/LC_MESSAGES/django.po
pretix_newsletter_ml/locale/zh_Hans/LC_MESSAGES/django.po
pretix_newsletter_ml/static/pretix_newsletter_ml/.gitkeep
pretix_newsletter_ml/templates/pretix_newsletter_ml/.gitkeep
pretix_newsletter_ml/templates/pretix_newsletter_ml/settings.html
pretix_newsletter_ml-1.4.1.dist-info/LICENSE
pretix_newsletter_ml-1.4.1.dist-info/METADATA
pretix_newsletter_ml-1.4.1.dist-info/WHEEL
pretix_newsletter_ml-1.4.1.dist-info/entry_points.txt
pretix_newsletter_ml-1.4.1.dist-info/top_level.txt
pretix_newsletter_ml-1.4.1.dist-info/RECORD
