Metadata-Version: 2.1
Name: pretix-newsletter-ml
Version: 1.4.1
Summary: pretix newsletter integration for mailing lists
Home-page: https://github.com/pretix/pretix-newsletter-ml
Author: Raphael Michel
Author-email: mail@raphaelmichel.de
License: Apache Software License
License-File: LICENSE
